xaivision/__init__.py
xaivision/nmf_func.py
xaivision/utils.py
xaivision/xai_tools.py
xaivision-0.5.4.dist-info/METADATA
xaivision-0.5.4.dist-info/WHEEL
xaivision-0.5.4.dist-info/RECORD
