Metadata-Version: 2.1
Name: xaivision
Version: 0.5.4
Summary: 
Author: philorfa
Author-email: phil.orfa@gmail.com
Requires-Python: >=3.11,<4.0
Classifier: Programming Language :: Python :: 3
Classifier: Programming Language :: Python :: 3.11
Classifier: Programming Language :: Python :: 3.12
